{
  "basic_mozes_bow": {
    "name"         : "Mozes' Bow",
    "group"        : "WEAPON",
    "sort"         : 1005,
    "skill"        : "MISSILE",
    "is_two_handed": true,
    "price"        : 3,
    "durability"   : 15,
    "min_dexterity": 10,
    "range"        : [6, 7, 8, 9],
    "base_hit"     : 80,
    "damage"       : 4
  },
  "basic_bow"      : {
    "name"         : "Basic Bow",
    "group"        : "WEAPON",
    "sort"         : 1400,
    "skill"        : "MISSILE",
    "is_two_handed": true,
    "price"        : 20,
    "durability"   : 30,
    "min_dexterity": 12,
    "range"        : [6, 7, 8, 9],
    "base_hit"     : 65,
    "damage"       : 5
  },
  "fine_bow"       : {
    "name"         : "Fine Bow",
    "group"        : "WEAPON",
    "sort"         : 2400,
    "skill"        : "MISSILE",
    "is_two_handed": true,
    "price"        : 40,
    "durability"   : 25,
    "min_dexterity": 18,
    "range"        : [6, 7, 8, 9],
    "base_hit"     : 55,
    "damage"       : 10
  },
  "specialist_bow" : {
    "name"         : "Specialist Bow",
    "group"        : "WEAPON",
    "sort"         : 3400,
    "skill"        : "MISSILE",
    "is_two_handed": true,
    "price"        : 60,
    "durability"   : 20,
    "min_dexterity": 24,
    "range"        : [6, 7, 8, 9],
    "base_hit"     : 45,
    "damage"       : 15
  },
  "masterwork_bow" : {
    "name"         : "Masterwork Bow",
    "group"        : "WEAPON",
    "sort"         : 4400,
    "skill"        : "MISSILE",
    "is_two_handed": true,
    "price"        : 80,
    "durability"   : 15,
    "min_dexterity": 30,
    "range"        : [6, 7, 8, 9],
    "base_hit"     : 35,
    "damage"       : 20
  }
}
